pants_py_deploy/__init__.py
pants_py_deploy/compose_file.py
pants_py_deploy/export_env.py
pants_py_deploy/fields.py
pants_py_deploy/models.py
pants_py_deploy/plugin.py
pants_py_deploy/register.py
pants_py_deploy-0.0.29.dist-info/METADATA
pants_py_deploy-0.0.29.dist-info/WHEEL
pants_py_deploy-0.0.29.dist-info/namespace_packages.txt
pants_py_deploy-0.0.29.dist-info/top_level.txt
pants_py_deploy-0.0.29.dist-info/RECORD
