Metadata-Version: 2.1
Name: pants-py-deploy
Version: 0.0.29
Summary: Make it easy to maintain docker-compose files and helm-charts across projects with pants-py-deploy
Home-page: https://github.com/EspenAlbert/py-libs
Author: Espen Albert
License: MIT
Classifier: Programming Language :: Python :: 3.9
Requires-Python: <3.10,>=3.9
Requires-Dist: compose-chart-export (==0.0.29)
Requires-Dist: docker-compose-parser (==0.0.29)
Requires-Dist: model-lib (==0.0.29)
Requires-Dist: pantsbuild.pants (<2.18,>=2.17.0a0)
Requires-Dist: zero-3rdparty (==0.0.29)
